quake_analyzer/__init__.py
quake_analyzer/cli.py
quake_analyzer-0.1.4.dist-info/licenses/LICENSE
quake_analyzer-0.1.4.dist-info/METADATA
quake_analyzer-0.1.4.dist-info/WHEEL
quake_analyzer-0.1.4.dist-info/entry_points.txt
quake_analyzer-0.1.4.dist-info/top_level.txt
quake_analyzer-0.1.4.dist-info/RECORD
