Metadata-Version: 2.4
Name: quake-analyzer
Version: 0.1.4
Summary: CLI tool to fetch and analyze earthquake data from USGS
Author: Daniel Haim
Project-URL: Homepage, https://github.com/danielhaim1/quake-analyzer
Project-URL: Repository, https://github.com/danielhaim1/quake-analyzer
Project-URL: Bug Tracker, https://github.com/danielhaim1/quake-analyzer/issues
Keywords: python,earthquakes,recursion,usgs,earthquake-data,usgs-data,earthquake-visualization,probability-statistics,earthquake-detection,usgs-earthquake
Classifier: Development Status :: 4 - Beta
Classifier: Intended Audience :: Science/Research
Classifier: Intended Audience :: Developers
Classifier: License :: OSI Approved :: MIT License
Classifier: Programming Language :: Python :: 3
Classifier: Programming Language :: Python :: 3.7
Classifier: Programming Language :: Python :: 3.8
Classifier: Programming Language :: Python :: 3.9
Classifier: Programming Language :: Python :: 3.10
Classifier: Programming Language :: Python :: 3.11
Classifier: Programming Language :: Python :: 3.12
Classifier: Operating System :: OS Independent
Classifier: Topic :: Scientific/Engineering :: GIS
Classifier: Topic :: Utilities
Classifier: Environment :: Console
Requires-Python: >=3.7
License-File: LICENSE
Requires-Dist: pandas
Requires-Dist: numpy
Requires-Dist: requests
Requires-Dist: matplotlib
Requires-Dist: colorama
Dynamic: license-file
Dynamic: requires-python
